auto_pytest_generator/__init__.py
auto_pytest_generator/addon.py
auto_pytest_generator/main.py
auto_pytest_generator/templates/pytest_template.jinja2
auto_pytest_generator-0.1.0.dist-info/licenses/LICENSE
auto_pytest_generator-0.1.0.dist-info/METADATA
auto_pytest_generator-0.1.0.dist-info/WHEEL
auto_pytest_generator-0.1.0.dist-info/entry_points.txt
auto_pytest_generator-0.1.0.dist-info/top_level.txt
auto_pytest_generator-0.1.0.dist-info/RECORD
