Metadata-Version: 2.4
Name: auto-pytest-generator
Version: 0.1.0
Summary: Generate pytest tests from captured fetch/XHR traffic via mitmproxy
Author-email: Chen Jianpeng <chenjianpeng97@outlook.com>
License: MIT
Requires-Python: >=3.8
License-File: LICENSE
Requires-Dist: mitmproxy
Requires-Dist: Jinja2
Requires-Dist: click
Dynamic: license-file
